xstac/__init__.py
xstac/_generate.py
xstac/_kerchunk.py
xstac/_xstac.py
xstac-1.2.0.dist-info/entry_points.txt
xstac-1.2.0.dist-info/WHEEL
xstac-1.2.0.dist-info/METADATA
xstac-1.2.0.dist-info/RECORD
