Metadata-Version: 2.1
Name: xstac
Version: 1.2.0
Summary: xstac
Author: Tom Augspurger
Author-email: tom.w.augspurger@gmail.com
Requires-Python: >=3.10
Classifier: License :: OSI Approved :: MIT License
Requires-Dist: cf_xarray
Requires-Dist: xarray
Requires-Dist: numpy
Requires-Dist: pystac>=1.0.0b3
Requires-Dist: pandas
Requires-Dist: pyproj
Requires-Dist: pydantic
Requires-Dist: zarr
Requires-Dist: jsonschema
Requires-Dist: dask[array]
Requires-Dist: fsspec[http]
Requires-Dist: pytest ; extra == "dev"
Requires-Dist: pre-commit ; extra == "dev"
Requires-Dist: shapely ; extra == "dev"
Requires-Dist: cftime ; extra == "dev"
Requires-Dist: kerchunk ; extra == "dev"
Requires-Dist: h5netcdf ; extra == "dev"
Requires-Dist: fsspec ; extra == "dev"
Provides-Extra: dev
